eduworld/__init__.py
eduworld/_internal/__init__.py
eduworld/_internal/application.py
eduworld/_internal/canvas.py
eduworld/_internal/plotter/__init__.py
eduworld/_internal/plotter/plottercanvas.py
eduworld/_internal/robot/__init__.py
eduworld/_internal/robot/algoworldboard.py
eduworld/_internal/robot/application.py
eduworld/_internal/robot/board.py
eduworld/_internal/robot/robot.py
eduworld/_internal/robot/robotcanvas.py
eduworld/_internal/robot/tile.py
eduworld/_internal/robot/tilemap.py
eduworld/_internal/robot/worlds/10x1.aww
eduworld/_internal/robot/worlds/10x10.aww
eduworld/_internal/robot/worlds/10x15.aww
eduworld/_internal/robot/worlds/20x20.aww
eduworld/_internal/robot/worlds/5x5.aww
eduworld/_internal/robot/worlds/demo-world.aww
eduworld/plotter/__init__.py
eduworld/robot/__init__.py
eduworld-0.0.40.dist-info/METADATA
eduworld-0.0.40.dist-info/WHEEL
eduworld-0.0.40.dist-info/licenses/LICENSE
eduworld-0.0.40.dist-info/RECORD
