Metadata-Version: 2.4
Name: EduWorld
Version: 0.0.40
Summary: Educational package to learn computational thinking and other basic programming concepts
Project-URL: Documentation, https://codeberg.org/helkaraxe/algoworld-python#readme
Project-URL: Issues, https://codeberg.org/helkaraxe/algoworld-python/issues
Project-URL: Source, https://codeberg.org/helkaraxe/algoworld-python
Author-email: Stanislav Grinkov <StanislavGrinkov@users.noreply.codeberg.org>
License-Expression: GPL-3.0-or-later
License-File: LICENSE
Keywords: beginners,computational thinking,education,gamification,learning
Classifier: Development Status :: 3 - Alpha
Classifier: Intended Audience :: Developers
Classifier: Intended Audience :: Education
Classifier: Programming Language :: Python
Classifier: Programming Language :: Python :: 3.8
Classifier: Programming Language :: Python :: 3.9
Classifier: Programming Language :: Python :: 3.10
Classifier: Programming Language :: Python :: 3.11
Classifier: Programming Language :: Python :: 3.12
Classifier: Programming Language :: Python :: 3.13
Requires-Python: >=3.8
